skyio/__init__.py
skyio/any_path.py
skyio/cloud_path.py
skyio/exceptions.py
skyio/generic_path.py
skyio/local_path.py
skyio/settings.py
skyio/singleton.py
skyio/utils.py
skyio/decor/__init__.py
skyio/decor/exception_decor.py
skyio/decor/type_assert_decor.py
skyio/vendors/__init__.py
skyio/vendors/gcp/__init__.py
skyio/vendors/gcp/gcp_cloud_path.py
skyio-1.0.1.dist-info/METADATA
skyio-1.0.1.dist-info/WHEEL
skyio-1.0.1.dist-info/RECORD
